ocr_engine/__init__.py
ocr_engine/common_pb2.py
ocr_engine/common_pb2_grpc.py
ocr_engine/grpc_client.py
ocr_engine/models.py
ocr_engine/ocrEngine_pb2.py
ocr_engine/ocrEngine_pb2_grpc.py
longleding_ocr_engine_sdk-0.1.3.dist-info/LICENSE
longleding_ocr_engine_sdk-0.1.3.dist-info/METADATA
longleding_ocr_engine_sdk-0.1.3.dist-info/WHEEL
longleding_ocr_engine_sdk-0.1.3.dist-info/top_level.txt
longleding_ocr_engine_sdk-0.1.3.dist-info/RECORD
