Metadata-Version: 2.1
Name: longleding-ocr-engine-sdk
Version: 0.1.3
Summary: Longleding OCR Engine SDK
Home-page: https://git.emhub.top/em/ocr-engine
Author: Shi Ran
Author-email: ran.shi@longleding.com
License: UNKNOWN
Platform: UNKNOWN
Classifier: Programming Language :: Python :: 3
Classifier: Topic :: System :: Logging
Requires-Python: >=3.6
